cclite/__init__.py
cclite/common_crawl.py
cclite-0.0.2.dist-info/LICENSE
cclite-0.0.2.dist-info/METADATA
cclite-0.0.2.dist-info/WHEEL
cclite-0.0.2.dist-info/top_level.txt
cclite-0.0.2.dist-info/RECORD
